pipeline_potato/__init__.py
pipeline_potato/pipeline.py
pipeline_potato/core/__init__.py
pipeline_potato/core/a_job.py
pipeline_potato/core/a_pipeline.py
pipeline_potato/core/a_potato.py
pipeline_potato/core/tasks_waiter.py
pipeline_potato/core/types.py
pipeline_potato/engine/__init__.py
pipeline_potato/engine/a_step_definition.py
pipeline_potato/engine/generics.py
pipeline_potato/engine/pipeline_bridge.py
pipeline_potato/engine/potato.py
pipeline_potato/engine/steps_definition_registry.py
pipeline_potato/engine/steps_registry.py
pipeline_potato/engine/jobs/__init__.py
pipeline_potato/engine/jobs/callback_job.py
pipeline_potato/engine/jobs/simple_job.py
pipeline_potato/enums/__init__.py
pipeline_potato/enums/job_state.py
pipeline_potato/enums/pipeline_state.py
pipeline_potato/enums/step_state.py
pipeline_potato/exceptions/__init__.py
pipeline_potato/exceptions/abort_exception.py
pipeline_potato/exceptions/action_out_of_context_exception.py
pipeline_potato/exceptions/circular_dependency_exception.py
pipeline_potato/exceptions/invalid_step_definition_exception.py
pipeline_potato/exceptions/potato_exception.py
pipeline_potato/exceptions/step_done_exception.py
pipeline_potato/exceptions/step_still_running_exception.py
pipeline_potato/graph/__init__.py
pipeline_potato/graph/steps_connection.py
pipeline_potato/graph/steps_graph.py
pipeline_potato/que/__init__.py
pipeline_potato/que/max_deque.py
pipeline_potato/que/potato_queue.py
pipeline_potato/steps/__init__.py
pipeline_potato/steps/entry_point.py
pipeline_potato/steps/step.py
pipeline_potato/steps/tree_traversal.py
pipeline_potato/steps/step_step/consume_queue_job.py
pipeline_potato/steps/step_tree_traversal/a_tree_traversal.py
pipeline_potato/steps/step_tree_traversal/tree_item.py
pipeline_potato/steps/step_tree_traversal/tree_traversal_job.py
pipeline_potato/steps/step_tree_traversal/tree_traversal_queue.py
pipeline_potato-1.0.1a1.dist-info/licenses/LICENSE
pipeline_potato-1.0.1a1.dist-info/METADATA
pipeline_potato-1.0.1a1.dist-info/WHEEL
pipeline_potato-1.0.1a1.dist-info/top_level.txt
pipeline_potato-1.0.1a1.dist-info/RECORD
