Metadata-Version: 2.4
Name: pipeline-potato
Version: 1.0.1a1
Summary: Lightweight, decorator-based async dataflow framework for high-concurrency ETL pipelines
Requires-Python: >=3.11
License-File: LICENSE
Provides-Extra: dev
Requires-Dist: pylint>=4.0.4; extra == "dev"
Requires-Dist: pytest>=8.4.1; extra == "dev"
Requires-Dist: pytest-cov>=6.2.1; extra == "dev"
Requires-Dist: pytest-asyncio>=1.1.0; extra == "dev"
Requires-Dist: pytest-timeout>=2.4.0; extra == "dev"
Requires-Dist: faker>=37.6.0; extra == "dev"
Requires-Dist: pyright>=1.1.0; extra == "dev"
Requires-Dist: check-wheel-contents>=0.6.3; extra == "dev"
Requires-Dist: twine>=6.2.0; extra == "dev"
Requires-Dist: build>=1.0.0; extra == "dev"
Dynamic: license-file
